cz_github_linear_conventional.py
cz_github_linear_conventional-1.4.1.dist-info/LICENSE
cz_github_linear_conventional-1.4.1.dist-info/METADATA
cz_github_linear_conventional-1.4.1.dist-info/WHEEL
cz_github_linear_conventional-1.4.1.dist-info/top_level.txt
cz_github_linear_conventional-1.4.1.dist-info/RECORD
