Metadata-Version: 2.1
Name: cz-github-linear-conventional
Version: 1.4.1
Summary: Extend the commitizen tools to create conventional commits and README that link to Linear.app and GitHub.
Home-page: https://github.com/ThimDeveloper/cz-github-linear-conventional
Author: Thim Lohse
Author-email: thim.lohse@caesari.se
License: MIT
Platform: unix
Platform: linux
Platform: osx
Platform: cygwin
Platform: win32
Classifier: Programming Language :: Python :: 3
Classifier: Programming Language :: Python :: 3 :: Only
Classifier: Programming Language :: Python :: 3.6
Classifier: Programming Language :: Python :: 3.7
Classifier: Programming Language :: Python :: 3.8
Classifier: Programming Language :: Python :: 3.9
Requires-Python: >=3.6
License-File: LICENSE
Requires-Dist: commitizen
Provides-Extra: testing
Requires-Dist: pytest (>=6.2.5) ; extra == 'testing'
Requires-Dist: flake8 (>=3.9) ; extra == 'testing'
